{
  "stats": {
    "suites": 1,
    "tests": 4,
    "passes": 4,
    "pending": 0,
    "failures": 0,
    "start": "2021-01-11T18:28:33.822Z",
    "end": "2021-01-11T18:28:35.790Z",
    "duration": 1856,
    "testsRegistered": 4,
    "passPercent": 100,
    "pendingPercent": 0,
    "other": 0,
    "hasOther": false,
    "skipped": 0,
    "hasSkipped": false
  },
  "results": [
    {
      "uuid": "a8453155-7537-48ec-995e-5be623da7ce8",
      "title": "",
      "fullFile": "cypress/integration/sortTableDom.spec.js",
      "file": "cypress/integration/sortTableDom.spec.js",
      "beforeHooks": [],
      "afterHooks": [],
      "tests": [],
      "suites": [
        {
          "uuid": "88eed2ed-cef7-4e5b-a72b-64590af2ff4f",
          "title": "Sorting table app",
          "fullFile": "",
          "file": "",
          "beforeHooks": [],
          "afterHooks": [],
          "tests": [
            {
              "title": "should sort in ASC order when user clicks on `Name` header",
              "fullTitle": "Sorting table app should sort in ASC order when user clicks on `Name` header",
              "timedOut": null,
              "duration": 785,
              "state": "passed",
              "speed": "slow",
              "pass": true,
              "fail": false,
              "pending": false,
              "context": null,
              "code": "cy.isSorted('Name', 1);",
              "err": {},
              "uuid": "c96ed372-07ef-4fd2-bf76-0d6f4fad46cb",
              "parentUUID": "88eed2ed-cef7-4e5b-a72b-64590af2ff4f",
              "isHook": false,
              "skipped": false
            },
            {
              "title": "should sort in ASC order when user clicks on `Position` header",
              "fullTitle": "Sorting table app should sort in ASC order when user clicks on `Position` header",
              "timedOut": null,
              "duration": 386,
              "state": "passed",
              "speed": "slow",
              "pass": true,
              "fail": false,
              "pending": false,
              "context": null,
              "code": "cy.isSorted('Position', 2);",
              "err": {},
              "uuid": "2c273c59-c2a6-47cc-9943-1d88a7fe701c",
              "parentUUID": "88eed2ed-cef7-4e5b-a72b-64590af2ff4f",
              "isHook": false,
              "skipped": false
            },
            {
              "title": "should sort in ASC order when user clicks on `Age` header",
              "fullTitle": "Sorting table app should sort in ASC order when user clicks on `Age` header",
              "timedOut": null,
              "duration": 331,
              "state": "passed",
              "speed": "slow",
              "pass": true,
              "fail": false,
              "pending": false,
              "context": null,
              "code": "cy.isSorted('Age', 3);",
              "err": {},
              "uuid": "e1d94511-29a5-43cf-abe1-8729d323d0c8",
              "parentUUID": "88eed2ed-cef7-4e5b-a72b-64590af2ff4f",
              "isHook": false,
              "skipped": false
            },
            {
              "title": "should sort in ASC order when user clicks on `Salary` header",
              "fullTitle": "Sorting table app should sort in ASC order when user clicks on `Salary` header",
              "timedOut": null,
              "duration": 354,
              "state": "passed",
              "speed": "slow",
              "pass": true,
              "fail": false,
              "pending": false,
              "context": null,
              "code": "cy.isSorted('Salary', 4);",
              "err": {},
              "uuid": "704c320a-ee6d-4ccd-a199-0989cd7072ae",
              "parentUUID": "88eed2ed-cef7-4e5b-a72b-64590af2ff4f",
              "isHook": false,
              "skipped": false
            }
          ],
          "suites": [],
          "passes": [
            "c96ed372-07ef-4fd2-bf76-0d6f4fad46cb",
            "2c273c59-c2a6-47cc-9943-1d88a7fe701c",
            "e1d94511-29a5-43cf-abe1-8729d323d0c8",
            "704c320a-ee6d-4ccd-a199-0989cd7072ae"
          ],
          "failures": [],
          "pending": [],
          "skipped": [],
          "duration": 1856,
          "root": false,
          "rootEmpty": false,
          "_timeout": 2000
        }
      ],
      "passes": [],
      "failures": [],
      "pending": [],
      "skipped": [],
      "duration": 0,
      "root": true,
      "rootEmpty": true,
      "_timeout": 2000
    }
  ],
  "meta": {
    "mocha": {
      "version": "7.0.1"
    },
    "mochawesome": {
      "options": {
        "quiet": false,
        "reportFilename": "mochawesome",
        "saveHtml": false,
        "saveJson": true,
        "consoleReporter": "spec",
        "useInlineDiffs": false,
        "code": true
      },
      "version": "6.2.1"
    },
    "marge": {
      "options": {
        "reportDir": "raw_reports",
        "overwrite": false,
        "html": false,
        "json": true
      },
      "version": "5.1.0"
    }
  }
}